nuts/__init__.py
nuts/_version.py
nuts/compute.py
nuts/too_event.py
nuts/too_observation.py
nuts/Catalogs/__init__.py
nuts/Catalogs/Database/SteadySources.csv
nuts/Catalogs/Database/__init__.py
nuts/Catalogs/General/GCN_alerts.csv
nuts/Catalogs/General/Priorities.csv
nuts/Catalogs/General/__init__.py
nuts/Catalogs/Listeners/__init__.py
nuts/Catalogs/Trajectories/__init__.py
nuts/IO_funcs/TSPRPST_database.py
nuts/IO_funcs/__init__.py
nuts/IO_funcs/get_kml.py
nuts/IO_funcs/json_input.py
nuts/IO_funcs/json_output.py
nuts/IO_funcs/prepare_db.py
nuts/IO_funcs/schemas.py
nuts/IO_funcs/too_database.py
nuts/UI/ATELS_reader.py
nuts/UI/README_GUI.md
nuts/UI/__init__.py
nuts/UI/add_source_GUI.py
nuts/UI/config_GUI.py
nuts/UI/getting_started_GUI.py
nuts/UI/listen_GUI.py
nuts/UI/obs_single_source_GUI.py
nuts/UI/run_GUI.py
nuts/UI/tabs_GUI.py
nuts/UI/too_method.png
nuts/UI/utils_GUI.py
nuts/UI/visuals_GUI.py
nuts/alert_listeners/GCN_alerts_template.py
nuts/alert_listeners/GCN_listener.py
nuts/alert_listeners/GCN_parser_methods.py
nuts/alert_listeners/TNS_download.py
nuts/alert_listeners/TNS_parser.py
nuts/alert_listeners/__init__.py
nuts/apps/UI.py
nuts/apps/__init__.py
nuts/apps/cli.py
nuts/apps/init.py
nuts/apps/kml_download.py
nuts/apps/listen.py
nuts/apps/make_config.py
nuts/apps/run.py
nuts/apps/single.py
nuts/config/__init__.py
nuts/config/config.py
nuts/config/file_config.py
nuts/config/load_config.py
nuts/config/logging_setup.py
nuts/detector_motion/__init__.py
nuts/detector_motion/constant_trajectory.py
nuts/detector_motion/detector.py
nuts/detector_motion/detector_init.py
nuts/detector_motion/detector_uptime.py
nuts/detector_motion/kml_trajectory.py
nuts/detector_motion/linear_trajectory.py
nuts/detector_motion/log_pointing.py
nuts/detector_motion/log_trajectory.py
nuts/detector_motion/satellite_trajectory.py
nuts/detector_motion/sim_trajectory.py
nuts/observation_period/__init__.py
nuts/observation_period/observability.py
nuts/observation_period/observation.py
too_nuts-0.3.post0.dist-info/licenses/LICENSE.txt
too_nuts-0.3.post0.dist-info/METADATA
too_nuts-0.3.post0.dist-info/WHEEL
too_nuts-0.3.post0.dist-info/entry_points.txt
too_nuts-0.3.post0.dist-info/top_level.txt
too_nuts-0.3.post0.dist-info/RECORD
