Metadata-Version: 2.4
Name: too-nuts
Version: 0.3.post0
Summary: Program to parse through neutrino source catalogs and select promising candidates to perform follow-up observations
Home-page: https://jem-euso.gitlab.io/euso-spb2/too/too-nuts
Author: EUSO-SPB2 ToO team
License: BSD-3-Clause-Clear
Keywords: Target of Opportunity,Scheduler,Neutrinos,POEMMA,JEM-EUSO
Classifier: Intended Audience :: Science/Research
Classifier: License :: OSI Approved :: BSD License
Classifier: Programming Language :: Python :: 3
Classifier: Programming Language :: Python :: 3 :: Only
Classifier: Programming Language :: Python :: 3.10
Classifier: Programming Language :: Python :: 3.11
Classifier: Programming Language :: Python :: 3.12
Classifier: Programming Language :: Python :: 3.13
Requires-Python: >=3.10
License-File: LICENSE.txt
Requires-Dist: numpy
Requires-Dist: matplotlib
Requires-Dist: attrs
Requires-Dist: astropy
Requires-Dist: influxdb_client
Requires-Dist: pandas
Requires-Dist: deepdiff
Requires-Dist: flatdict
Requires-Dist: gcn_kafka
Requires-Dist: fiona
Requires-Dist: geopandas
Requires-Dist: scipy
Requires-Dist: pytest
Requires-Dist: toml
Requires-Dist: pathlib
Requires-Dist: click
Requires-Dist: pre-commit
Requires-Dist: pydantic
Requires-Dist: tomli_w
Requires-Dist: streamlit
Requires-Dist: streamlit_pdf_viewer
Requires-Dist: healpy
Requires-Dist: tqdm
Requires-Dist: cartopy
Requires-Dist: h5py
Requires-Dist: pathlib
Dynamic: license-file
